Modules/Azure.py
Modules/Cloud.py
Modules/GCP.py
Modules/__init__.py
arthurstonecli-0.1.data/scripts/stone_cli
arthurstonecli-0.1.dist-info/METADATA
arthurstonecli-0.1.dist-info/WHEEL
arthurstonecli-0.1.dist-info/top_level.txt
arthurstonecli-0.1.dist-info/RECORD
